{
  "type": "object",
  "comment": "ListView",
  "properties": {
    "listItems": {
      "type": "array",
      "items": {
        "type": "object",
        "properties": {
          "shipmentNumber": {
            "type": "string",
            "update": {
              "type": "none"
            },
            "selector": "td",
            "control": "property.innerText"
          },
          "packageNumber": {
            "type": "string",
            "selectIndex": 1,
            "selector": "td",
            "control": "property.innerText"
          },
          "trackingNumber": {
            "type": "string",
            "selector": "td",
            "control": "property.innerText",
            "selectIndex": 2
          },
          "project": {
            "type": "string",
            "selector": "td",
            "control": "property.innerText",
            "selectIndex": 3
          },
          "creationDate": {
            "type": "string",
            "selector": "td",
            "control": "property.innerText",
            "selectIndex": 4
          },
          "searchResultClick": {
            "type": "action",
            "selector": "td",
            "control": "action.click"
          }
        }
      },
      "update": {
        "type": "none"
      },
      "selectorAll": "#SearchResult > table > tbody > tr"
    },
    "isSearchResult": {
      "type": "string",
      "selector": "#resultDetails",
      "control": "exists"
    }
  },
  "connect": []
}
